<?xml version="1.0"?>
<save_state>
	<input />
	<window />
	<textures />
	<audio />
	<:anonymous />
	<pathfinding />
	<scene />
	<map />
	<entitymanager>
		<entities>
			<Enemy x="59.7999992" y="64.7850189">
				<velocity x="0" y="0" />
			</Enemy>
			<Enemy x="40.6000023" y="64.7850189">
				<velocity x="0" y="0" />
			</Enemy>
			<Player x="30" y="64.7850189" jump="0">
				<velocity x="0" y="0" />
			</Player>
		</entities>
	</entitymanager>
	<titleScene />
	<logoScene />
	<fade />
	<renderer>
		<camera x="62" y="-607" />
	</renderer>
</save_state>
